<?xml version="1.0" encoding="UTF-8"?>
<objects serializationModel="Studio.02.02.00">
	<object class="EncodingSetting" id="{30e6fd4d-c300-49a1-8b8f-a73b8c2b9456}">
		<property name="encodingFormat">
			<value>3</value>
		</property>
		<property name="quality">
			<value>37</value>
		</property>
		<relationship name="platform">
			<destination>{db854026-77c5-4051-a583-ceaf072e9bf9}</destination>
		</relationship>
		<relationship name="encodable">
			<destination>{db854026-77c5-4051-a583-ceaf072e9bf9}</destination>
		</relationship>
	</object>
</objects>
